{"better_top": [{"username": "Curse Inc.", "amount": 20000}, {"username": "lenis0012", "amount": 3081}, {"username": "vilsol", "amount": 2872}, {"username": "SLiPCoR", "amount": 2750}, {"username": "alkarinv", "amount": 2500}, {"username": "DSH105", "amount": 2123}, {"username": "PaulBGD", "amount": 1664}, {"username": "sgtcaze", "amount": 790}, {"username": "games647", "amount": 501}, {"username": "mbaxter", "amount": 493}, {"username": "hawkfalcon", "amount": 411}, {"username": "lDucks", "amount": 392}, {"username": "chaseoes", "amount": 368}, {"username": "jorisk322", "amount": 347}, {"username": "jkcclemens", "amount": 273}, {"username": "DevRosemberg", "amount": 237}, {"username": "kezz101", "amount": 230}, {"username": "robbo5899", "amount": 223}, {"username": "vemacs", "amount": 199}, {"username": "tacticalsk8er", "amount": 177}, {"username": "JOPHESTUS", "amount": 176}, {"username": "Xboxmods", "amount": 160}, {"username": "Hoolean", "amount": 139}, {"username": "lol768", "amount": 137}, {"username": "tyzoid", "amount": 135}, {"username": "Miner_Fil", "amount": 128}, {"username": "Garris0n", "amount": 117}, {"username": "Bionicrm", "amount": 111}, {"username": "Axe2760", "amount": 108}, {"username": "mazentheamazin", "amount": 100}, {"username": "AeroUK", "amount": 94}, {"username": "TeddyTheTeddy", "amount": 94}, {"username": "iKeirNez", "amount": 91}, {"username": "ZeusAllMighty11", "amount": 71}, {"username": "Squidicc", "amount": 58}, {"username": "nlthijs48", "amount": 57}, {"username": "ShadowWizardMC", "amount": 56}, {"username": "MACOSX24", "amount": 49}, {"username": "libraryaddict", "amount": 48}, {"username": "TehKitti", "amount": 38}, {"username": "mrCookieSlime", "amount": 34}, {"username": "MylesC", "amount": 34}, {"username": "se1by", "amount": 27}, {"username": "datdenkikniet", "amount": 25}, {"username": "Chinwe", "amount": 25}, {"username": "Archarin", "amount": 25}, {"username": "Ad237", "amount": 20}, {"username": "Dippoakabob", "amount": 20}, {"username": "hintss", "amount": 20}, {"username": "SupaHam", "amount": 19}, {"username": "instipod", "amount": 18}, {"username": "CaptainBern", "amount": 15}, {"username": "viper_monster", "amount": 14}, {"username": "MineOCraftMC", "amount": 13}, {"username": "evilmidget38", "amount": 12}, {"username": "ZodiacTheories", "amount": 10}, {"username": "Synapzz", "amount": 10}, {"username": "inventorman101", "amount": 10}, {"username": "connorlinfoot", "amount": 8}, {"username": "rigor789", "amount": 7}, {"username": "DeprecatedNether", "amount": 6}, {"username": "legostarwarszach", "amount": 5}, {"username": "Scrayos", "amount": 5}, {"username": "xCyanide", "amount": 5}, {"username": "LaxWasHere", "amount": 3}, {"username": "RenegadeEagle", "amount": 3}, {"username": "daboross", "amount": 2}, {"username": "Dpasi314", "amount": 1}, {"username": "bendembd", "amount": 1}, {"username": "MrTang", "amount": 1}, {"username": "BDKing00", "amount": 1}, {"username": "RainoBoy97", "amount": 1}, {"username": "Skyost", "amount": 1}, {"username": "AbsolutesGamers", "amount": 1}], "last_update": 1409426630, "top_donors": {"lenis0012": 3081, "vilsol": 2872, "SLiPCoR": 2750, "alkarinv": 2500, "DSH105": 2123, "PaulBGD": 1664, "sgtcaze": 790, "games647": 501, "mbaxter": 493, "hawkfalcon": 411, "lDucks": 392, "chaseoes": 368, "jorisk322": 347, "jkcclemens": 273, "DevRosemberg": 237, "kezz101": 230, "robbo5899": 223, "vemacs": 199, "tacticalsk8er": 177, "JOPHESTUS": 176, "Xboxmods": 160, "Hoolean": 139, "lol768": 137, "tyzoid": 135, "Miner_Fil": 128, "Garris0n": 117, "Bionicrm": 111, "Axe2760": 108, "mazentheamazin": 100, "AeroUK": 94, "TeddyTheTeddy": 94, "iKeirNez": 91, "ZeusAllMighty11": 71, "Squidicc": 58, "nlthijs48": 57, "ShadowWizardMC": 56, "MACOSX24": 49, "libraryaddict": 48, "TehKitti": 38, "mrCookieSlime": 34, "MylesC": 34, "se1by": 27, "datdenkikniet": 25, "Chinwe": 25, "Archarin": 25, "Ad237": 20, "Dippoakabob": 20, "hintss": 20, "SupaHam": 19, "instipod": 18, "CaptainBern": 15, "viper_monster": 14, "MineOCraftMC": 13, "evilmidget38": 12, "ZodiacTheories": 10, "Synapzz": 10, "inventorman101": 10, "connorlinfoot": 8, "rigor789": 7, "DeprecatedNether": 6, "legostarwarszach": 5, "Scrayos": 5, "xCyanide": 5, "LaxWasHere": 3, "RenegadeEagle": 3, "daboross": 2, "Dpasi314": 1, "bendembd": 1, "MrTang": 1, "BDKing00": 1, "RainoBoy97": 1, "Skyost": 1, "AbsolutesGamers": 1}, "points": 42000, "recent_transactions": [{"username": "mbaxter", "amount": 463, "curse-timestamp": "1409356800"}, {"username": "JOPHESTUS", "amount": 8, "curse-timestamp": "1409097600"}, {"username": "JOPHESTUS", "amount": 3, "curse-timestamp": "1408492800"}, {"username": "games647", "amount": 400, "curse-timestamp": "1408406400"}, {"username": "games647", "amount": 101, "curse-timestamp": "1408406400"}, {"username": "iKeirNez", "amount": 14, "curse-timestamp": "1408406400"}, {"username": "JOPHESTUS", "amount": 6, "curse-timestamp": "1408406400"}, {"username": "lDucks", "amount": 4, "curse-timestamp": "1408320000"}, {"username": "Bionicrm", "amount": 1, "curse-timestamp": "1408233600"}, {"username": "robbo5899", "amount": 25, "curse-timestamp": "1408060800"}, {"username": "lol768", "amount": 7, "curse-timestamp": "1408060800"}, {"username": "jkcclemens", "amount": 26, "curse-timestamp": "1408060800"}, {"username": "JOPHESTUS", "amount": 3, "curse-timestamp": "1407974400"}, {"username": "JOPHESTUS", "amount": 9, "curse-timestamp": "1407801600"}, {"username": "lol768", "amount": 5, "curse-timestamp": "1407542400"}, {"username": "JOPHESTUS", "amount": 7, "curse-timestamp": "1407283200"}, {"username": "lol768", "amount": 2, "curse-timestamp": "1407196800"}, {"username": "lol768", "amount": 9, "curse-timestamp": "1407024000"}, {"username": "mbaxter", "amount": 1, "curse-timestamp": "1406937600"}, {"username": "JOPHESTUS", "amount": 2, "curse-timestamp": "1406764800"}, {"username": "DSH105", "amount": 386, "curse-timestamp": "1406764800"}, {"username": "jkcclemens", "amount": 14, "curse-timestamp": "1406764800"}, {"username": "JOPHESTUS", "amount": 26, "curse-timestamp": "1406678400"}, {"username": "jkcclemens", "amount": 11, "curse-timestamp": "1406332800"}, {"username": "lol768", "amount": 8, "curse-timestamp": "1406332800"}, {"username": "lol768", "amount": 10, "curse-timestamp": "1405814400"}, {"username": "jkcclemens", "amount": 19, "curse-timestamp": "1405814400"}, {"username": "lDucks", "amount": 1, "curse-timestamp": "1405382400"}, {"username": "robbo5899", "amount": 8, "curse-timestamp": "1405296000"}, {"username": "iKeirNez", "amount": 1, "curse-timestamp": "1405209600"}, {"username": "lDucks", "amount": 1, "curse-timestamp": "1405209600"}, {"username": "Scrayos", "amount": 5, "curse-timestamp": "1405123200"}, {"username": "mbaxter", "amount": 1, "curse-timestamp": "1405123200"}, {"username": "JOPHESTUS", "amount": 1, "curse-timestamp": "1405123200"}, {"username": "LaxWasHere", "amount": 1, "curse-timestamp": "1405123200"}, {"username": "lol768", "amount": 2, "curse-timestamp": "1405123200"}, {"username": "iKeirNez", "amount": 3, "curse-timestamp": "1405036800"}, {"username": "Ad237", "amount": 20, "curse-timestamp": "1405036800"}, {"username": "JOPHESTUS", "amount": 4, "curse-timestamp": "1405036800"}, {"username": "PaulBGD", "amount": 190, "curse-timestamp": "1404950400"}, {"username": "jkcclemens", "amount": 4, "curse-timestamp": "1404950400"}, {"username": "lol768", "amount": 4, "curse-timestamp": "1404950400"}, {"username": "DevRosemberg", "amount": 1, "curse-timestamp": "1404950400"}, {"username": "libraryaddict", "amount": 4, "curse-timestamp": "1404950400"}, {"username": "Bionicrm", "amount": 2, "curse-timestamp": "1404864000"}, {"username": "DevRosemberg", "amount": 3, "curse-timestamp": "1404864000"}, {"username": "connorlinfoot", "amount": 8, "curse-timestamp": "1404864000"}, {"username": "jkcclemens", "amount": 2, "curse-timestamp": "1404864000"}, {"username": "JOPHESTUS", "amount": 2, "curse-timestamp": "1404777600"}, {"username": "lenis0012", "amount": 154, "curse-timestamp": "1404777600"}, {"username": "mbaxter", "amount": 7, "curse-timestamp": "1404777600"}, {"username": "Dpasi314", "amount": 1, "curse-timestamp": "1404691200"}, {"username": "chaseoes", "amount": 268, "curse-timestamp": "1404691200"}, {"username": "hawkfalcon", "amount": 7, "curse-timestamp": "1404691200"}, {"username": "Garris0n", "amount": 17, "curse-timestamp": "1404691200"}, {"username": "CaptainBern", "amount": 6, "curse-timestamp": "1404691200"}, {"username": "robbo5899", "amount": 91, "curse-timestamp": "1404691200"}, {"username": "jkcclemens", "amount": 1, "curse-timestamp": "1404691200"}, {"username": "bendembd", "amount": 1, "curse-timestamp": "1404691200"}, {"username": "DSH105", "amount": 15, "curse-timestamp": "1404691200"}, {"username": "lol768", "amount": 1, "curse-timestamp": "1404691200"}, {"username": "SLiPCoR", "amount": 250, "curse-timestamp": "1404691200"}, {"username": "JOPHESTUS", "amount": 5, "curse-timestamp": "1404691200"}, {"username": "DevRosemberg", "amount": 233, "curse-timestamp": "1404691200"}, {"username": "lDucks", "amount": 2, "curse-timestamp": "1404604800"}, {"username": "libraryaddict", "amount": 44, "curse-timestamp": "1404604800"}, {"username": "Bionicrm", "amount": 8, "curse-timestamp": "1404604800"}, {"username": "DSH105", "amount": 607, "curse-timestamp": "1404604800"}, {"username": "sgtcaze", "amount": 790, "curse-timestamp": "1404604800"}, {"username": "TeddyTheTeddy", "amount": 1, "curse-timestamp": "1404604800"}, {"username": "vilsol", "amount": 72, "curse-timestamp": "1404604800"}, {"username": "jkcclemens", "amount": 2, "curse-timestamp": "1404604800"}, {"username": "instipod", "amount": 18, "curse-timestamp": "1404604800"}, {"username": "lol768", "amount": 1, "curse-timestamp": "1404604800"}, {"username": "Dippoakabob", "amount": 20, "curse-timestamp": "1404604800"}, {"username": "SupaHam", "amount": 19, "curse-timestamp": "1404518400"}, {"username": "lol768", "amount": 2, "curse-timestamp": "1404518400"}, {"username": "jkcclemens", "amount": 6, "curse-timestamp": "1404518400"}, {"username": "LaxWasHere", "amount": 2, "curse-timestamp": "1404518400"}, {"username": "lol768", "amount": 1, "curse-timestamp": "1404432000"}, {"username": "ZodiacTheories", "amount": 10, "curse-timestamp": "1404432000"}, {"username": "robbo5899", "amount": 99, "curse-timestamp": "1404432000"}, {"username": "nlthijs48", "amount": 57, "curse-timestamp": "1404432000"}, {"username": "lol768", "amount": 2, "curse-timestamp": "1404345600"}, {"username": "iKeirNez", "amount": 12, "curse-timestamp": "1404345600"}, {"username": "JOPHESTUS", "amount": 6, "curse-timestamp": "1404345600"}, {"username": "jkcclemens", "amount": 2, "curse-timestamp": "1404259200"}, {"username": "MACOSX24", "amount": 49, "curse-timestamp": "1404259200"}, {"username": "lol768", "amount": 3, "curse-timestamp": "1404172800"}, {"username": "jkcclemens", "amount": 1, "curse-timestamp": "1404172800"}, {"username": "hawkfalcon", "amount": 23, "curse-timestamp": "1404172800"}, {"username": "TeddyTheTeddy", "amount": 11, "curse-timestamp": "1404086400"}, {"username": "jkcclemens", "amount": 2, "curse-timestamp": "1404086400"}, {"username": "lenis0012", "amount": 727, "curse-timestamp": "1404086400"}, {"username": "JOPHESTUS", "amount": 3, "curse-timestamp": "1404086400"}, {"username": "tacticalsk8er", "amount": 177, "curse-timestamp": "1404086400"}, {"username": "jkcclemens", "amount": 2, "curse-timestamp": "1404000000"}, {"username": "lol768", "amount": 2, "curse-timestamp": "1404000000"}, {"username": "jkcclemens", "amount": 6, "curse-timestamp": "1403913600"}, {"username": "JOPHESTUS", "amount": 3, "curse-timestamp": "1403827200"}, {"username": "lol768", "amount": 3, "curse-timestamp": "1403827200"}, {"username": "Skyost", "amount": 1, "curse-timestamp": "1403740800"}, {"username": "lol768", "amount": 2, "curse-timestamp": "1403654400"}, {"username": "JOPHESTUS", "amount": 4, "curse-timestamp": "1403654400"}, {"username": "jkcclemens", "amount": 4, "curse-timestamp": "1403654400"}, {"username": "jkcclemens", "amount": 11, "curse-timestamp": "1403481600"}, {"username": "lol768", "amount": 1, "curse-timestamp": "1403481600"}, {"username": "lol768", "amount": 2, "curse-timestamp": "1403395200"}, {"username": "JOPHESTUS", "amount": 3, "curse-timestamp": "1403395200"}, {"username": "xCyanide", "amount": 5, "curse-timestamp": "1403395200"}, {"username": "lol768", "amount": 2, "curse-timestamp": "1403308800"}, {"username": "legostarwarszach", "amount": 5, "curse-timestamp": "1403222400"}, {"username": "JOPHESTUS", "amount": 2, "curse-timestamp": "1403222400"}, {"username": "JOPHESTUS", "amount": 2, "curse-timestamp": "1403136000"}, {"username": "lol768", "amount": 2, "curse-timestamp": "1403136000"}, {"username": "jkcclemens", "amount": 2, "curse-timestamp": "1403049600"}, {"username": "Bionicrm", "amount": 10, "curse-timestamp": "1403049600"}, {"username": "lol768", "amount": 1, "curse-timestamp": "1403049600"}, {"username": "JOPHESTUS", "amount": 1, "curse-timestamp": "1403049600"}, {"username": "SLiPCoR", "amount": 500, "curse-timestamp": "1403049600"}, {"username": "jkcclemens", "amount": 4, "curse-timestamp": "1402963200"}, {"username": "lol768", "amount": 4, "curse-timestamp": "1402963200"}, {"username": "JOPHESTUS", "amount": 2, "curse-timestamp": "1402963200"}, {"username": "lDucks", "amount": 1, "curse-timestamp": "1402876800"}, {"username": "JOPHESTUS", "amount": 8, "curse-timestamp": "1402876800"}, {"username": "jkcclemens", "amount": 3, "curse-timestamp": "1402790400"}, {"username": "lol768", "amount": 1, "curse-timestamp": "1402704000"}, {"username": "jkcclemens", "amount": 2, "curse-timestamp": "1402704000"}, {"username": "jkcclemens", "amount": 2, "curse-timestamp": "1402617600"}, {"username": "lol768", "amount": 4, "curse-timestamp": "1402617600"}, {"username": "Squidicc", "amount": 58, "curse-timestamp": "1402617600"}, {"username": "jkcclemens", "amount": 2, "curse-timestamp": "1402531200"}, {"username": "Archarin", "amount": 25, "curse-timestamp": "1402531200"}, {"username": "lDucks", "amount": 1, "curse-timestamp": "1402444800"}, {"username": "jkcclemens", "amount": 2, "curse-timestamp": "1402444800"}, {"username": "JOPHESTUS", "amount": 3, "curse-timestamp": "1402444800"}, {"username": "Axe2760", "amount": 108, "curse-timestamp": "1402444800"}, {"username": "vemacs", "amount": 199, "curse-timestamp": "1402358400"}, {"username": "rigor789", "amount": 7, "curse-timestamp": "1402358400"}, {"username": "hawkfalcon", "amount": 7, "curse-timestamp": "1402358400"}, {"username": "lol768", "amount": 2, "curse-timestamp": "1402358400"}, {"username": "jkcclemens", "amount": 2, "curse-timestamp": "1402358400"}, {"username": "jkcclemens", "amount": 5, "curse-timestamp": "1402272000"}, {"username": "JOPHESTUS", "amount": 3, "curse-timestamp": "1402272000"}, {"username": "Miner_Fil", "amount": 128, "curse-timestamp": "1402272000"}, {"username": "lol768", "amount": 2, "curse-timestamp": "1402185600"}, {"username": "tyzoid", "amount": 135, "curse-timestamp": "1402185600"}, {"username": "hintss", "amount": 20, "curse-timestamp": "1402185600"}, {"username": "JOPHESTUS", "amount": 4, "curse-timestamp": "1402185600"}, {"username": "jkcclemens", "amount": 4, "curse-timestamp": "1402099200"}, {"username": "BDKing00", "amount": 1, "curse-timestamp": "1402099200"}, {"username": "DeprecatedNether", "amount": 1, "curse-timestamp": "1402099200"}, {"username": "Synapzz", "amount": 10, "curse-timestamp": "1402099200"}, {"username": "lol768", "amount": 1, "curse-timestamp": "1402099200"}, {"username": "mrCookieSlime", "amount": 13, "curse-timestamp": "1402099200"}, {"username": "iKeirNez", "amount": 61, "curse-timestamp": "1402012800"}, {"username": "mrCookieSlime", "amount": 21, "curse-timestamp": "1402012800"}, {"username": "se1by", "amount": 27, "curse-timestamp": "1402012800"}, {"username": "lol768", "amount": 1, "curse-timestamp": "1402012800"}, {"username": "jkcclemens", "amount": 3, "curse-timestamp": "1402012800"}, {"username": "ShadowWizardMC", "amount": 1, "curse-timestamp": "1401926400"}, {"username": "ShadowWizardMC", "amount": 5, "curse-timestamp": "1401926400"}, {"username": "datdenkikniet", "amount": 25, "curse-timestamp": "1401926400"}, {"username": "lol768", "amount": 2, "curse-timestamp": "1401926400"}, {"username": "JOPHESTUS", "amount": 1, "curse-timestamp": "1401926400"}, {"username": "PaulBGD", "amount": 1, "curse-timestamp": "1401840000"}, {"username": "SLiPCoR", "amount": 500, "curse-timestamp": "1401840000"}, {"username": "jkcclemens", "amount": 2, "curse-timestamp": "1401840000"}, {"username": "lol768", "amount": 1, "curse-timestamp": "1401840000"}, {"username": "hawkfalcon", "amount": 16, "curse-timestamp": "1401840000"}, {"username": "lDucks", "amount": 2, "curse-timestamp": "1401840000"}, {"username": "JOPHESTUS", "amount": 1, "curse-timestamp": "1401840000"}, {"username": "JOPHESTUS", "amount": 1, "curse-timestamp": "1401840000"}, {"username": "JOPHESTUS", "amount": 1, "curse-timestamp": "1401840000"}, {"username": "JOPHESTUS", "amount": 1, "curse-timestamp": "1401840000"}, {"username": "JOPHESTUS", "amount": 1, "curse-timestamp": "1401840000"}, {"username": "JOPHESTUS", "amount": 1, "curse-timestamp": "1401840000"}, {"username": "JOPHESTUS", "amount": 1, "curse-timestamp": "1401840000"}, {"username": "lol768", "amount": 1, "curse-timestamp": "1401753600"}, {"username": "jkcclemens", "amount": 2, "curse-timestamp": "1401753600"}, {"username": "jkcclemens", "amount": 2, "curse-timestamp": "1401753600"}, {"username": "lol768", "amount": 2, "curse-timestamp": "1401667200"}, {"username": "jkcclemens", "amount": 3, "curse-timestamp": "1401494400"}, {"username": "lol768", "amount": 1, "curse-timestamp": "1401494400"}, {"username": "ZeusAllMighty11", "amount": 71, "curse-timestamp": "1401408000"}, {"username": "Bionicrm", "amount": 90, "curse-timestamp": "1401408000"}, {"username": "RenegadeEagle", "amount": 3, "curse-timestamp": "1401408000"}, {"username": "DSH105", "amount": 169, "curse-timestamp": "1401408000"}, {"username": "TehKitti", "amount": 1, "curse-timestamp": "1401408000"}, {"username": "jkcclemens", "amount": 3, "curse-timestamp": "1401408000"}, {"username": "lol768", "amount": 2, "curse-timestamp": "1401408000"}, {"username": "JOPHESTUS", "amount": 9, "curse-timestamp": "1401408000"}, {"username": "jkcclemens", "amount": 2, "curse-timestamp": "1401408000"}, {"username": "lol768", "amount": 1, "curse-timestamp": "1401408000"}, {"username": "MylesC", "amount": 5, "curse-timestamp": "1401321600"}, {"username": "MylesC", "amount": 1, "curse-timestamp": "1401321600"}, {"username": "MylesC", "amount": 6, "curse-timestamp": "1401321600"}, {"username": "MylesC", "amount": 22, "curse-timestamp": "1401321600"}, {"username": "kezz101", "amount": 230, "curse-timestamp": "1401321600"}, {"username": "Hoolean", "amount": 139, "curse-timestamp": "1401235200"}, {"username": "jkcclemens", "amount": 3, "curse-timestamp": "1401235200"}, {"username": "lol768", "amount": 2, "curse-timestamp": "1401235200"}, {"username": "viper_monster", "amount": 14, "curse-timestamp": "1401235200"}, {"username": "vilsol", "amount": 1300, "curse-timestamp": "1401148800"}, {"username": "AbsolutesGamers", "amount": 1, "curse-timestamp": "1401148800"}, {"username": "jkcclemens", "amount": 3, "curse-timestamp": "1401148800"}, {"username": "lol768", "amount": 3, "curse-timestamp": "1401148800"}, {"username": "lenis0012", "amount": 2200, "curse-timestamp": "1401062400"}, {"username": "RainoBoy97", "amount": 1, "curse-timestamp": "1401062400"}, {"username": "JOPHESTUS", "amount": 4, "curse-timestamp": "1401062400"}, {"username": "jkcclemens", "amount": 2, "curse-timestamp": "1401062400"}, {"username": "jkcclemens", "amount": 3, "curse-timestamp": "1400976000"}, {"username": "lol768", "amount": 1, "curse-timestamp": "1400976000"}, {"username": "SLiPCoR", "amount": 50, "curse-timestamp": "1400976000"}, {"username": "ShadowWizardMC", "amount": 45, "curse-timestamp": "1400976000"}, {"username": "ShadowWizardMC", "amount": 5, "curse-timestamp": "1400976000"}, {"username": "jorisk322", "amount": 347, "curse-timestamp": "1400976000"}, {"username": "Xboxmods", "amount": 160, "curse-timestamp": "1400889600"}, {"username": "TehKitti", "amount": 37, "curse-timestamp": "1400889600"}, {"username": "inventorman101", "amount": 10, "curse-timestamp": "1400889600"}, {"username": "mbaxter", "amount": 5, "curse-timestamp": "1400803200"}, {"username": "mbaxter", "amount": 4, "curse-timestamp": "1400803200"}, {"username": "mbaxter", "amount": 3, "curse-timestamp": "1400803200"}, {"username": "mbaxter", "amount": 2, "curse-timestamp": "1400803200"}, {"username": "mbaxter", "amount": 1, "curse-timestamp": "1400803200"}, {"username": "PaulBGD", "amount": 1, "curse-timestamp": "1400803200"}, {"username": "PaulBGD", "amount": 1, "curse-timestamp": "1400803200"}, {"username": "PaulBGD", "amount": 1, "curse-timestamp": "1400803200"}, {"username": "PaulBGD", "amount": 1, "curse-timestamp": "1400803200"}, {"username": "PaulBGD", "amount": 1, "curse-timestamp": "1400803200"}, {"username": "lol768", "amount": 1, "curse-timestamp": "1400803200"}, {"username": "JOPHESTUS", "amount": 3, "curse-timestamp": "1400803200"}, {"username": "Chinwe", "amount": 25, "curse-timestamp": "1400803200"}, {"username": "jkcclemens", "amount": 2, "curse-timestamp": "1400803200"}, {"username": "PaulBGD", "amount": 1, "curse-timestamp": "1400803200"}, {"username": "PaulBGD", "amount": 1, "curse-timestamp": "1400803200"}, {"username": "PaulBGD", "amount": 1, "curse-timestamp": "1400803200"}, {"username": "PaulBGD", "amount": 1, "curse-timestamp": "1400803200"}, {"username": "PaulBGD", "amount": 1, "curse-timestamp": "1400803200"}, {"username": "PaulBGD", "amount": 126, "curse-timestamp": "1400803200"}, {"username": "daboross", "amount": 2, "curse-timestamp": "1400716800"}, {"username": "jkcclemens", "amount": 3, "curse-timestamp": "1400716800"}, {"username": "SLiPCoR", "amount": 36, "curse-timestamp": "1400716800"}, {"username": "lol768", "amount": 2, "curse-timestamp": "1400716800"}, {"username": "mbaxter", "amount": 1, "curse-timestamp": "1400716800"}, {"username": "evilmidget38", "amount": 2, "curse-timestamp": "1400716800"}, {"username": "evilmidget38", "amount": 2, "curse-timestamp": "1400716800"}, {"username": "hawkfalcon", "amount": 1, "curse-timestamp": "1400716800"}, {"username": "evilmidget38", "amount": 2, "curse-timestamp": "1400716800"}, {"username": "evilmidget38", "amount": 2, "curse-timestamp": "1400716800"}, {"username": "evilmidget38", "amount": 2, "curse-timestamp": "1400716800"}, {"username": "evilmidget38", "amount": 2, "curse-timestamp": "1400716800"}, {"username": "mbaxter", "amount": 1, "curse-timestamp": "1400716800"}, {"username": "mbaxter", "amount": 1, "curse-timestamp": "1400716800"}, {"username": "mbaxter", "amount": 1, "curse-timestamp": "1400716800"}, {"username": "mbaxter", "amount": 1, "curse-timestamp": "1400716800"}, {"username": "mbaxter", "amount": 1, "curse-timestamp": "1400716800"}, {"username": "AeroUK", "amount": 94, "curse-timestamp": "1400630400"}, {"username": "jkcclemens", "amount": 2, "curse-timestamp": "1400630400"}, {"username": "MrTang", "amount": 1, "curse-timestamp": "1400630400"}, {"username": "JOPHESTUS", "amount": 2, "curse-timestamp": "1400630400"}, {"username": "DSH105", "amount": 1, "curse-timestamp": "1400630400"}, {"username": "lol768", "amount": 1, "curse-timestamp": "1400630400"}, {"username": "SLiPCoR", "amount": 614, "curse-timestamp": "1400630400"}, {"username": "Garris0n", "amount": 31, "curse-timestamp": "1400630400"}, {"username": "Garris0n", "amount": 69, "curse-timestamp": "1400630400"}, {"username": "MineOCraftMC", "amount": 13, "curse-timestamp": "1400630400"}, {"username": "PaulBGD", "amount": 1337, "curse-timestamp": "1400630400"}, {"username": "chaseoes", "amount": 100, "curse-timestamp": "1400544000"}, {"username": "alkarinv", "amount": 2500, "curse-timestamp": "1400544000"}, {"username": "lDucks", "amount": 200, "curse-timestamp": "1400544000"}, {"username": "jkcclemens", "amount": 97, "curse-timestamp": "1400544000"}, {"username": "lDucks", "amount": 180, "curse-timestamp": "1400544000"}, {"username": "mazentheamazin", "amount": 100, "curse-timestamp": "1400544000"}, {"username": "vilsol", "amount": 1500, "curse-timestamp": "1400544000"}, {"username": "hawkfalcon", "amount": 357, "curse-timestamp": "1400544000"}, {"username": "DeprecatedNether", "amount": 5, "curse-timestamp": "1400544000"}, {"username": "TeddyTheTeddy", "amount": 82, "curse-timestamp": "1400544000"}, {"username": "DSH105", "amount": 645, "curse-timestamp": "1400544000"}, {"username": "SLiPCoR", "amount": 800, "curse-timestamp": "1400544000"}, {"username": "CaptainBern", "amount": 9, "curse-timestamp": "1400544000"}, {"username": "DSH105", "amount": 300, "curse-timestamp": "1400544000"}, {"username": "JOPHESTUS", "amount": 30, "curse-timestamp": "1400544000"}, {"username": "lol768", "amount": 30, "curse-timestamp": "1400544000"}], "next_update": 1409427230}